et_micc_build/__init__.py
et_micc_build/cli_micc_build.py
et_micc_build-1.1.8.dist-info/entry_points.txt
et_micc_build-1.1.8.dist-info/LICENSE
et_micc_build-1.1.8.dist-info/WHEEL
et_micc_build-1.1.8.dist-info/METADATA
et_micc_build-1.1.8.dist-info/RECORD
