Metadata-Version: 2.1
Name: et-micc-build
Version: 1.1.8
Summary: CLI micc-build and module for building binary extensions created with micc.
Home-page: https://github.com/etijskens/et-micc-build
License: MIT
Keywords: packaging,poetry
Author: Engelbert Tijskens
Author-email: engelbert.tijskens@uantwerpen.be
Requires-Python: >=3.6,<4.0
Classifier: License :: OSI Approved :: MIT License
Classifier: Programming Language :: Python :: 3
Classifier: Programming Language :: Python :: 3.6
Classifier: Programming Language :: Python :: 3.7
Classifier: Programming Language :: Python :: 3.8
Classifier: Programming Language :: Python :: 3.9
Requires-Dist: et-micc (==1.1.8)
Requires-Dist: numpy (>=1.17.0,<2.0.0)
Requires-Dist: pybind11 (>=2.6.1,<3.0.0)
Project-URL: Repository, https://github.com/etijskens/et-micc-build
